sirqle/__init__.py
sirqle/config.py
sirqle/query.py
sirqle-0.4.4.dist-info/LICENSE
sirqle-0.4.4.dist-info/METADATA
sirqle-0.4.4.dist-info/WHEEL
sirqle-0.4.4.dist-info/top_level.txt
sirqle-0.4.4.dist-info/RECORD
