Metadata-Version: 2.1
Name: sirqle
Version: 0.4.4
Summary: SurrealDB Query Interface
Author-email: Pythia Dev Team <dev@pythia.social>
License: Apache License
Project-URL: Source, https://github.com/PythiaSocialTech/sirqle
Requires-Python: >=3.8
License-File: LICENSE
Requires-Dist: python-dotenv
Requires-Dist: surrealdb2 >=0.3.2
Provides-Extra: dev
Requires-Dist: pre-commit ; extra == 'dev'
Requires-Dist: pytest ; extra == 'dev'
Requires-Dist: pytest-asyncio ; extra == 'dev'
Requires-Dist: pytest-dependency ; extra == 'dev'
Requires-Dist: commitizen ; extra == 'dev'
Requires-Dist: flit ; extra == 'dev'
Requires-Dist: Faker ; extra == 'dev'
Provides-Extra: docs
Requires-Dist: mkdocs ; extra == 'docs'
Requires-Dist: mkdocstrings ; extra == 'docs'
Requires-Dist: mkdocs-material ; extra == 'docs'
Requires-Dist: mkdocs-literate-nav ; extra == 'docs'
Requires-Dist: mkdocstrings[python] >=0.18 ; extra == 'docs'
Requires-Dist: mkdocs-gen-files ; extra == 'docs'
